tagging/sqlite/__init__.py
tagging/sqlite/tagging.py
volttron_sqlite_tagging-0.1.1a0.dist-info/entry_points.txt
volttron_sqlite_tagging-0.1.1a0.dist-info/WHEEL
volttron_sqlite_tagging-0.1.1a0.dist-info/METADATA
volttron_sqlite_tagging-0.1.1a0.dist-info/RECORD
