Metadata-Version: 2.1
Name: volttron-sqlite-tagging
Version: 0.1.1a0
Summary: Tagging agent that implement volttron-lib-tagging and store tag data in sqlite3 database
Home-page: https://github.com/eclipse-volttron/volttron-sqlite-tagging
License: Apache-2.0
Author: VOLTTRON Team
Author-email: volttron@pnnl.gov
Requires-Python: >=3.10,<4.0
Classifier: License :: OSI Approved :: Apache Software License
Classifier: Programming Language :: Python :: 3
Classifier: Programming Language :: Python :: 3.10
Classifier: Programming Language :: Python :: 3.11
Requires-Dist: ply (>=3.11,<4.0)
Requires-Dist: volttron-lib-tagging (>=0.1.1a2,<0.2.0)
Project-URL: Repository, https://github.com/eclipse-volttron/volttron-sqlite-tagging
